ml_package/__init__.py
simple_ml_api-0.1.0.dist-info/METADATA
simple_ml_api-0.1.0.dist-info/WHEEL
simple_ml_api-0.1.0.dist-info/entry_points.txt
simple_ml_api-0.1.0.dist-info/top_level.txt
simple_ml_api-0.1.0.dist-info/RECORD
