Metadata-Version: 2.1
Name: simple-ml-api
Version: 0.1.0
Summary: A simple Flask API for doubling a value
Home-page: UNKNOWN
Author: Your Name
License: UNKNOWN
Platform: UNKNOWN
Requires-Python: >=3.7
Requires-Dist: flask
